ewmhlib/Props.py
ewmhlib/Structs.py
ewmhlib/__init__.py
ewmhlib/_ewmhlib.py
ewmhlib/_main.py
ewmhlib/py.typed
pywinbox/__init__.py
pywinbox/_main.py
pywinbox/_pywinbox_linux.py
pywinbox/_pywinbox_macos.py
pywinbox/_pywinbox_win.py
pywinbox/py.typed
PyWinBox-0.5.dist-info/AUTHORS.txt
PyWinBox-0.5.dist-info/LICENSE.txt
PyWinBox-0.5.dist-info/METADATA
PyWinBox-0.5.dist-info/WHEEL
PyWinBox-0.5.dist-info/top_level.txt
PyWinBox-0.5.dist-info/RECORD
